wepps/__init__.py
wepps/app.py
wepps/site.py
wepps/utilities.py
wepps/stage/parameters.py
wepps/stage/stages.py
wepps/stage/utils.py
wepps/static/favicon.ico
wepps/static/manifest.json
wepps/static/assets/KaTeX_AMS-Regular-0cdd387c.woff2
wepps/static/assets/KaTeX_AMS-Regular-30da91e8.woff
wepps/static/assets/KaTeX_AMS-Regular-68534840.ttf
wepps/static/assets/KaTeX_Caligraphic-Bold-07d8e303.ttf
wepps/static/assets/KaTeX_Caligraphic-Bold-1ae6bd74.woff
wepps/static/assets/KaTeX_Caligraphic-Bold-de7701e4.woff2
wepps/static/assets/KaTeX_Caligraphic-Regular-3398dd02.woff
wepps/static/assets/KaTeX_Caligraphic-Regular-5d53e70a.woff2
wepps/static/assets/KaTeX_Caligraphic-Regular-ed0b7437.ttf
wepps/static/assets/KaTeX_Fraktur-Bold-74444efd.woff2
wepps/static/assets/KaTeX_Fraktur-Bold-9163df9c.ttf
wepps/static/assets/KaTeX_Fraktur-Bold-9be7ceb8.woff
wepps/static/assets/KaTeX_Fraktur-Regular-1e6f9579.ttf
wepps/static/assets/KaTeX_Fraktur-Regular-51814d27.woff2
wepps/static/assets/KaTeX_Fraktur-Regular-5e28753b.woff
wepps/static/assets/KaTeX_Main-Bold-0f60d1b8.woff2
wepps/static/assets/KaTeX_Main-Bold-138ac28d.ttf
wepps/static/assets/KaTeX_Main-Bold-c76c5d69.woff
wepps/static/assets/KaTeX_Main-BoldItalic-70ee1f64.ttf
wepps/static/assets/KaTeX_Main-BoldItalic-99cd42a3.woff2
wepps/static/assets/KaTeX_Main-BoldItalic-a6f7ec0d.woff
wepps/static/assets/KaTeX_Main-Italic-0d85ae7c.ttf
wepps/static/assets/KaTeX_Main-Italic-97479ca6.woff2
wepps/static/assets/KaTeX_Main-Italic-f1d6ef86.woff
wepps/static/assets/KaTeX_Main-Regular-c2342cd8.woff2
wepps/static/assets/KaTeX_Main-Regular-c6368d87.woff
wepps/static/assets/KaTeX_Main-Regular-d0332f52.ttf
wepps/static/assets/KaTeX_Math-BoldItalic-850c0af5.woff
wepps/static/assets/KaTeX_Math-BoldItalic-dc47344d.woff2
wepps/static/assets/KaTeX_Math-BoldItalic-f9377ab0.ttf
wepps/static/assets/KaTeX_Math-Italic-08ce98e5.ttf
wepps/static/assets/KaTeX_Math-Italic-7af58c5e.woff2
wepps/static/assets/KaTeX_Math-Italic-8a8d2445.woff
wepps-0.2.0.dist-info/METADATA
wepps-0.2.0.dist-info/WHEEL
wepps-0.2.0.dist-info/licenses/LICENSE
wepps-0.2.0.dist-info/RECORD
